{
  "languageModel": {
    "intents": [
      {
        "name": "AMAZON.CancelIntent",
        "samples": []
      },
      {
        "name": "AMAZON.HelpIntent",
        "samples": []
      },
      {
        "name": "AMAZON.StopIntent",
        "samples": []
      },
      {
        "name": "AMAZON.YesIntent",
        "samples": []
      },
      {
        "name": "AnswerIntent",
        "samples": [
          "{number}",
          "the answer is {number}"
        ],
        "slots": [
          {
            "name": "number",
            "type": "AMAZON.NUMBER"
          }
        ]
      },
      {
        "name": "SetTimesTables",
        "samples": [
          "I want to practice my {number} times tables",
          "help me with my {number} times table",
          "test me on my {number} times tables"
        ],
        "slots": [
          {
            "name": "number",
            "type": "AMAZON.NUMBER"
          }
        ]
      }
    ],
    "invocationName": "maths helper"
  }
}